{
  "_note1": "KEEP THIS FILE! Check it into a version control system (VCS) like git.",
  "_note2": "ObjectBox manages crucial IDs for your object model. See docs for details.",
  "_note3": "If you have VCS merge conflicts, you must resolve them according to ObjectBox docs.",
  "entities": [
    {
      "id": "1:7083872728731314041",
      "lastPropertyId": "4:4448834129399354701",
      "name": "GoArea",
      "properties": [
        {
          "id": "1:7555529911993090175",
          "name": "id",
          "type": 6,
          "flags": 1
        },
        {
          "id": "2:4943808412432512183",
          "name": "name",
          "type": 9
        },
        {
          "id": "3:2923049207995111230",
          "name": "latitudes",
          "type": 29
        },
        {
          "id": "4:4448834129399354701",
          "name": "longitudes",
          "type": 29
        }
      ],
      "relations": []
    },
    {
      "id": "2:5050029956017223729",
      "lastPropertyId": "9:6045908418656766656",
      "name": "GoChurch",
      "properties": [
        {
          "id": "1:2109843755976065155",
          "name": "id",
          "type": 6,
          "flags": 1
        },
        {
          "id": "2:4539052346717228295",
          "name": "churchName",
          "type": 9
        },
        {
          "id": "3:6389136498818712415",
          "name": "pastorName",
          "type": 9
        },
        {
          "id": "4:6324976360314074494",
          "name": "address",
          "type": 9
        },
        {
          "id": "5:7222681513442131998",
          "name": "phone",
          "type": 9
        },
        {
          "id": "6:6497726387861986683",
          "name": "email",
          "type": 9
        },
        {
          "id": "7:2775343986583367378",
          "name": "latitude",
          "type": 8
        },
        {
          "id": "8:5045419863412287382",
          "name": "longitude",
          "type": 8
        },
        {
          "id": "9:6045908418656766656",
          "name": "financialStatus",
          "type": 9
        }
      ],
      "relations": [
        {
          "id": "1:1573175650678576808",
          "name": "notes",
          "targetId": "3:5931460527089354068"
        }
      ]
    },
    {
      "id": "3:5931460527089354068",
      "lastPropertyId": "5:4786621687177879903",
      "name": "GoChurchNote",
      "properties": [
        {
          "id": "1:7791099989165109565",
          "name": "id",
          "type": 6,
          "flags": 1
        },
        {
          "id": "2:5266784726653752051",
          "name": "content",
          "type": 9
        },
        {
          "id": "3:6956167979864031910",
          "name": "createdAt",
          "type": 10
        },
        {
          "id": "4:6725205937780954991",
          "name": "updatedAt",
          "type": 10
        },
        {
          "id": "5:4786621687177879903",
          "name": "churchId",
          "type": 11,
          "flags": 520,
          "indexId": "1:3217273838086944322",
          "relationTarget": "GoChurch"
        }
      ],
      "relations": []
    },
    {
      "id": "4:1976238399811454903",
      "lastPropertyId": "10:5492261088621745955",
      "name": "GoContact",
      "properties": [
        {
          "id": "1:3246437018319147865",
          "name": "id",
          "type": 6,
          "flags": 1
        },
        {
          "id": "2:1970161832864079532",
          "name": "fullName",
          "type": 9
        },
        {
          "id": "3:5058969624732999991",
          "name": "latitude",
          "type": 8
        },
        {
          "id": "4:5080513681103903791",
          "name": "longitude",
          "type": 8
        },
        {
          "id": "5:1270337556774670396",
          "name": "address",
          "type": 9
        },
        {
          "id": "6:4100270960635311988",
          "name": "birthday",
          "type": 9
        },
        {
          "id": "7:5925916583683823247",
          "name": "phone",
          "type": 9
        },
        {
          "id": "8:8361651124882179207",
          "name": "email",
          "type": 9
        },
        {
          "id": "9:6101197022842561259",
          "name": "isVisited",
          "type": 1
        },
        {
          "id": "10:5492261088621745955",
          "name": "eternalStatus",
          "type": 9
        }
      ],
      "relations": [
        {
          "id": "2:6074900501751078089",
          "name": "notes",
          "targetId": "5:3058574985031740746"
        }
      ]
    },
    {
      "id": "5:3058574985031740746",
      "lastPropertyId": "5:889019147383687410",
      "name": "GoContactNote",
      "properties": [
        {
          "id": "1:2377228935996550504",
          "name": "id",
          "type": 6,
          "flags": 1
        },
        {
          "id": "2:4908825658542136097",
          "name": "content",
          "type": 9
        },
        {
          "id": "3:7760783191000802768",
          "name": "createdAt",
          "type": 10
        },
        {
          "id": "4:3932812695752990695",
          "name": "updatedAt",
          "type": 10
        },
        {
          "id": "5:889019147383687410",
          "name": "contactId",
          "type": 11,
          "flags": 520,
          "indexId": "2:9011361943251959944",
          "relationTarget": "GoContact"
        }
      ],
      "relations": []
    },
    {
      "id": "6:2665787256503988678",
      "lastPropertyId": "8:40494082937438136",
      "name": "GoMapInfo",
      "properties": [
        {
          "id": "1:8028310876346673732",
          "name": "id",
          "type": 6,
          "flags": 1
        },
        {
          "id": "2:1516100658783480286",
          "name": "name",
          "type": 9
        },
        {
          "id": "3:3867507740522120033",
          "name": "filePath",
          "type": 9
        },
        {
          "id": "4:7402950179089979190",
          "name": "downloadUrl",
          "type": 9
        },
        {
          "id": "5:5928405830910816327",
          "name": "isTemporary",
          "type": 1
        },
        {
          "id": "6:8059496525490497351",
          "name": "latitude",
          "type": 8
        },
        {
          "id": "7:2173698251270163742",
          "name": "longitude",
          "type": 8
        },
        {
          "id": "8:40494082937438136",
          "name": "zoomLevel",
          "type": 6
        }
      ],
      "relations": []
    },
    {
      "id": "7:4865298318050831300",
      "lastPropertyId": "9:4699597435329766236",
      "name": "GoMinistry",
      "properties": [
        {
          "id": "1:2612846044076694330",
          "name": "id",
          "type": 6,
          "flags": 1
        },
        {
          "id": "2:6151925275336806164",
          "name": "ministryName",
          "type": 9
        },
        {
          "id": "3:4090028621276882559",
          "name": "contactName",
          "type": 9
        },
        {
          "id": "4:6730347334833529782",
          "name": "address",
          "type": 9
        },
        {
          "id": "5:501592972262879572",
          "name": "phone",
          "type": 9
        },
        {
          "id": "6:751000587074202212",
          "name": "email",
          "type": 9
        },
        {
          "id": "7:6944413280855457412",
          "name": "latitude",
          "type": 8
        },
        {
          "id": "8:5024297062089877426",
          "name": "longitude",
          "type": 8
        },
        {
          "id": "9:4699597435329766236",
          "name": "partnerStatus",
          "type": 9
        }
      ],
      "relations": [
        {
          "id": "3:1309935384823613763",
          "name": "notes",
          "targetId": "8:2285190532305431564"
        }
      ]
    },
    {
      "id": "8:2285190532305431564",
      "lastPropertyId": "5:7943790696315202208",
      "name": "GoMinistryNote",
      "properties": [
        {
          "id": "1:6507141856073701705",
          "name": "id",
          "type": 6,
          "flags": 1
        },
        {
          "id": "2:3943523326673005596",
          "name": "content",
          "type": 9
        },
        {
          "id": "3:8260294369889000382",
          "name": "createdAt",
          "type": 10
        },
        {
          "id": "4:825326408118433407",
          "name": "updatedAt",
          "type": 10
        },
        {
          "id": "5:7943790696315202208",
          "name": "ministryId",
          "type": 11,
          "flags": 520,
          "indexId": "3:3886804655405571653",
          "relationTarget": "GoMinistry"
        }
      ],
      "relations": []
    },
    {
      "id": "9:8427369011552153197",
      "lastPropertyId": "4:664828791450709974",
      "name": "GoStreet",
      "properties": [
        {
          "id": "1:2906474675922369265",
          "name": "id",
          "type": 6,
          "flags": 1
        },
        {
          "id": "2:3387593211098263899",
          "name": "name",
          "type": 9
        },
        {
          "id": "3:8359970019001797576",
          "name": "latitudes",
          "type": 29
        },
        {
          "id": "4:664828791450709974",
          "name": "longitudes",
          "type": 29
        }
      ],
      "relations": []
    },
    {
      "id": "10:5359052010570933925",
      "lastPropertyId": "6:1407901165240966597",
      "name": "GoZone",
      "properties": [
        {
          "id": "1:5948834156975079035",
          "name": "id",
          "type": 6,
          "flags": 1
        },
        {
          "id": "2:4495209025648478734",
          "name": "name",
          "type": 9
        },
        {
          "id": "3:891053469472926468",
          "name": "latitude",
          "type": 8
        },
        {
          "id": "4:8337833787715567382",
          "name": "longitude",
          "type": 8
        },
        {
          "id": "5:109439213147209262",
          "name": "widthInMeters",
          "type": 8
        },
        {
          "id": "6:1407901165240966597",
          "name": "heightInMeters",
          "type": 8
        }
      ],
      "relations": []
    },
    {
      "id": "11:565910807588908638",
      "lastPropertyId": "4:2948240853486109615",
      "name": "UserPreferences",
      "properties": [
        {
          "id": "1:6229356501338400978",
          "name": "id",
          "type": 6,
          "flags": 1
        },
        {
          "id": "2:159770327866303893",
          "name": "currentMap",
          "type": 9
        },
        {
          "id": "3:632482109552115707",
          "name": "fontFamily",
          "type": 9
        },
        {
          "id": "4:2948240853486109615",
          "name": "fontSize",
          "type": 8
        }
      ],
      "relations": []
    }
  ],
  "lastEntityId": "11:565910807588908638",
  "lastIndexId": "3:3886804655405571653",
  "lastRelationId": "3:1309935384823613763",
  "lastSequenceId": "0:0",
  "modelVersion": 5,
  "modelVersionParserMinimum": 5,
  "retiredEntityUids": [],
  "retiredIndexUids": [],
  "retiredPropertyUids": [],
  "retiredRelationUids": [],
  "version": 1
}